<?xml version="1.0" encoding="utf-8" ?>
<dwsync>
<file name="favicon.ico" server="C:/AppServ/www/contrast/" local="130173580320000000" remote="130173580320000000" Dst="-1" />
<file name="index.html" server="C:/AppServ/www/contrast/" local="130174024837924055" remote="130174024830000000" Dst="-1" />
<file name="favicon.ico" server="207.45.190.206/public_html/wahabjawed/" local="130173652320000000" remote="130390587600000000" Dst="0" />
<file name="resume.html" server="207.45.190.206/public_html/wahabjawed/" local="130391172988523872" remote="130390814400000000" Dst="0" />
<file name="contact.html" server="207.45.190.206/public_html/wahabjawed/" local="130391172987933479" remote="130390813800000000" Dst="0" />
<file name="index.html" server="207.45.190.206/public_html/wahabjawed/" local="130403342454513880" remote="130403029800000000" Dst="0" />
<file name="work.html" server="207.45.190.206/public_html/wahabjawed/" local="130403388692474283" remote="130403065200000000" Dst="0" />
<file name="project-1.html" server="207.45.190.206/public_html/wahabjawed/" local="130181973397580626" remote="130390587600000000" Dst="0" />
<file name="project-2.html" server="207.45.190.206/public_html/wahabjawed/" local="130181973497105321" remote="130390587600000000" Dst="0" />
<file name="project-3.html" server="207.45.190.206/public_html/wahabjawed/" local="130181973595799785" remote="130390587600000000" Dst="0" />
<file name="themeok.org.url" server="207.45.190.206/public_html/wahabjawed/" local="129897806296066254" remote="130390587600000000" Dst="0" />
</dwsync>